atsphinx/helper/__init__.py
atsphinx/helper/decorators.py
atsphinx_helper-0.1.1.dist-info/METADATA
atsphinx_helper-0.1.1.dist-info/WHEEL
atsphinx_helper-0.1.1.dist-info/RECORD
