Metadata-Version: 2.4
Name: atsphinx-helper
Version: 0.1.1
Summary: Helper for my Sphinx extension
Project-URL: Home, https://github.com/atsphinx/helper
Project-URL: Repository, https://github.com/atsphinx/helper
Project-URL: Issues, https://github.com/atsphinx/helper/issues
Project-URL: Changelog, https://github.com/atsphinx/helper/blob/main/CHANGELOG.md
Author-email: Kazuya Takei <myself@attakei.net>
License-Expression: Apache-2.0
Classifier: Development Status :: 3 - Alpha
Classifier: Framework :: Sphinx
Classifier: Framework :: Sphinx :: Extension
Classifier: Intended Audience :: Developers
Classifier: License :: OSI Approved :: Apache Software License
Classifier: Operating System :: OS Independent
Classifier: Programming Language :: Python
Classifier: Programming Language :: Python :: 3 :: Only
Classifier: Programming Language :: Python :: 3.9
Classifier: Programming Language :: Python :: 3.10
Classifier: Programming Language :: Python :: 3.11
Classifier: Programming Language :: Python :: 3.12
Classifier: Programming Language :: Python :: 3.13
Classifier: Topic :: Documentation :: Sphinx
Requires-Python: >=3.9
Requires-Dist: sphinx
